GoogleJavascriptFenggeZhinan/README.md
GoogleJavascriptFenggeZhinan/__init__.py
GoogleJavascriptFenggeZhinan/__main__.py
GoogleJavascriptFenggeZhinan/file.epub
GoogleJavascriptFenggeZhinan/index.html
GoogleJavascriptFenggeZhinan/css/__init__.py
GoogleJavascriptFenggeZhinan/css/annotations.css
GoogleJavascriptFenggeZhinan/css/main.css
GoogleJavascriptFenggeZhinan/css/normalize.css
GoogleJavascriptFenggeZhinan/css/popup.css
GoogleJavascriptFenggeZhinan/font/__init__.py
GoogleJavascriptFenggeZhinan/font/fontello.eot
GoogleJavascriptFenggeZhinan/font/fontello.svg
GoogleJavascriptFenggeZhinan/font/fontello.ttf
GoogleJavascriptFenggeZhinan/font/fontello.woff
GoogleJavascriptFenggeZhinan/img/__init__.py
GoogleJavascriptFenggeZhinan/img/annotator-glyph-sprite.png
GoogleJavascriptFenggeZhinan/img/annotator-icon-sprite.png
GoogleJavascriptFenggeZhinan/img/apple-touch-icon.png
GoogleJavascriptFenggeZhinan/img/cancelfullscreen.png
GoogleJavascriptFenggeZhinan/img/close.png
GoogleJavascriptFenggeZhinan/img/fullscreen.png
GoogleJavascriptFenggeZhinan/img/loader.gif
GoogleJavascriptFenggeZhinan/img/menu-icon.png
GoogleJavascriptFenggeZhinan/img/save.png
GoogleJavascriptFenggeZhinan/img/saved.png
GoogleJavascriptFenggeZhinan/img/settings-s.png
GoogleJavascriptFenggeZhinan/img/settings.png
GoogleJavascriptFenggeZhinan/img/star.png
GoogleJavascriptFenggeZhinan/js/__init__.py
GoogleJavascriptFenggeZhinan/js/epub.js
GoogleJavascriptFenggeZhinan/js/epub.min.js
GoogleJavascriptFenggeZhinan/js/epub.min.map
GoogleJavascriptFenggeZhinan/js/hooks.min.js
GoogleJavascriptFenggeZhinan/js/hooks.min.map
GoogleJavascriptFenggeZhinan/js/reader.js
GoogleJavascriptFenggeZhinan/js/reader.js.map
GoogleJavascriptFenggeZhinan/js/reader.min.js
GoogleJavascriptFenggeZhinan/js/reader.min.map
GoogleJavascriptFenggeZhinan/js/hooks/__init__.py
GoogleJavascriptFenggeZhinan/js/hooks/extensions/__init__.py
GoogleJavascriptFenggeZhinan/js/hooks/extensions/highlight.js
google_javascript_fengge_zhinan-2024.3.1.0.dist-info/METADATA
google_javascript_fengge_zhinan-2024.3.1.0.dist-info/WHEEL
google_javascript_fengge_zhinan-2024.3.1.0.dist-info/entry_points.txt
google_javascript_fengge_zhinan-2024.3.1.0.dist-info/top_level.txt
google_javascript_fengge_zhinan-2024.3.1.0.dist-info/RECORD
